pw_zoomus
